crud_repository/__config__.py
crud_repository/__init__.py
crud_repository/db/__init__.py
crud_repository/db/factory.py
crud_repository/db/idatabase.py
crud_repository/db/mariadb/__init__.py
crud_repository/db/mariadb/db.py
crud_repository/db/mysql/__init__.py
crud_repository/db/mysql/db.py
crud_repository/db/postgres/__init__.py
crud_repository/db/postgres/db.py
crud_repository/model/__init__.py
crud_repository/model/base.py
crud_repository/my_logger/__init__.py
crud_repository/my_logger/formatters.py
crud_repository/my_logger/handlers.py
crud_repository/my_logger/logger.py
crud_repository/my_logger/monitor.py
crud_repository/repo/__init__.py
crud_repository/repo/repository.py
crud_repository-0.2.3.dist-info/LICENSE
crud_repository-0.2.3.dist-info/METADATA
crud_repository-0.2.3.dist-info/WHEEL
crud_repository-0.2.3.dist-info/top_level.txt
crud_repository-0.2.3.dist-info/RECORD
