Metadata-Version: 2.1
Name: crud_repository
Version: 0.2.3
Summary: The CRUDRepository is a Python project designed to provide a generic implementation of Create, Read, Update, and Delete (CRUD) operations for various databases.
Home-page: https://github.com/dellius-alexander/CRUDRepository.git
Author: Dellius Alexander
Author-email: Dellius Alexander <dalexander@hyfisolutions.com>, info@hyfisolutions.com
Maintainer-email: Dellius Alexander <dalexander@hyfisolutions.com>
License: MIT License
Project-URL: Homepage, https://github.com/dellius-alexander/CRUDRepository.git
Keywords: crud-repository,database,model,abstraction,sqlalchemy
Classifier: Development Status :: 3 - Alpha
Classifier: Intended Audience :: Developers
Classifier: License :: OSI Approved :: MIT License
Classifier: Programming Language :: Python :: 3.8
Classifier: Programming Language :: Python :: 3.9
Classifier: Programming Language :: Python :: 3.10
Classifier: Programming Language :: Python :: 3.11
Classifier: Operating System :: OS Independent
License-File: LICENSE
Requires-Dist: sqlalchemy >=2.0.29
Requires-Dist: psycopg2-binary >=2.9.9
Requires-Dist: python-dotenv >=1.0.1
Requires-Dist: colorlog >=6.4.1
Requires-Dist: cryptography >=42.0.5
Requires-Dist: pymysql >=1.1.0
Requires-Dist: SQLAlchemy-Utils >=0.41.2
